README.rst
setup.py
DowPy.egg-info/PKG-INFO
DowPy.egg-info/SOURCES.txt
DowPy.egg-info/dependency_links.txt
DowPy.egg-info/not-zip-safe
DowPy.egg-info/requires.txt
DowPy.egg-info/top_level.txt
dowpy/__init__.py
dowpy/dow.py
dowpy.egg-info/PKG-INFO
dowpy.egg-info/SOURCES.txt
dowpy.egg-info/dependency_links.txt
dowpy.egg-info/not-zip-safe
dowpy.egg-info/requires.txt
dowpy.egg-info/top_level.txt