Metadata-Version: 1.0
Name: DowPy
Version: 0.1.6
Summary: Module for downloading files over HTTP(s) efficiently
Home-page: https://pypi.org/project/dowpy/
Author: JohnBrunelle
Author-email: devjohnb@gmail.com
License: MIT
Platform: UNKNOWN
